LICENSE
MANIFEST.in
README.md
requirements.txt
setup.py
uos_statphys/ImportManager.py
uos_statphys/__init__.py
uos_statphys/isingModel.py
uos_statphys/viscekModel.py
uos_statphys.egg-info/PKG-INFO
uos_statphys.egg-info/SOURCES.txt
uos_statphys.egg-info/dependency_links.txt
uos_statphys.egg-info/requires.txt
uos_statphys.egg-info/top_level.txt
uos_statphys/Analyzer/__init__.py
uos_statphys/Analyzer/markov.py
uos_statphys/C_ext/__init__.py
uos_statphys/lib/src/dSFMT-common.h
uos_statphys/lib/src/dSFMT-params.h
uos_statphys/lib/src/dSFMT-params19937.h
uos_statphys/lib/src/dSFMT.c
uos_statphys/lib/src/dSFMT.h
uos_statphys/lib/src/dllmain.cpp
uos_statphys/lib/src/isingmonte.cpp