Metadata-Version: 1.2
Name: uos-statphys
Version: 0.1.6
Summary: Python library for statistical physics lab of University of Seoul.
Home-page: UNKNOWN
Author: Junghoon Jung
Author-email: jh.jung@uos.ac.kr
License: UNKNOWN
Platform: UNKNOWN
Requires-Python: >=3
